dbt/__init__.py
dbt/adapters/infer/__init__.py
dbt/adapters/infer/__version__.py
dbt/adapters/infer/connections.py
dbt/adapters/infer/impl.py
dbt/include/infer/__init__.py
dbt/include/infer/dbt_project.yml
dbt/include/infer/profile_template.yml
dbt/include/infer/macros/adapters.sql
dbt/include/infer/macros/catalog.sql
dbt_infer-1.6.0.dist-info/LICENSE
dbt_infer-1.6.0.dist-info/METADATA
dbt_infer-1.6.0.dist-info/WHEEL
dbt_infer-1.6.0.dist-info/top_level.txt
dbt_infer-1.6.0.dist-info/RECORD
