Metadata-Version: 2.1
Name: dbt-infer
Version: 1.6.0
Summary: The Infer adapter plugin for dbt
Home-page: https://github.com/inferlabs/dbt-infer
Author: Infer
Author-email: support@inferlabs.io
License: UNKNOWN
Platform: UNKNOWN
Classifier: Development Status :: 5 - Production/Stable
Classifier: License :: OSI Approved :: Apache Software License
Classifier: Operating System :: Microsoft :: Windows
Classifier: Operating System :: MacOS :: MacOS X
Classifier: Operating System :: POSIX :: Linux
Classifier: Programming Language :: Python :: 3.7
Classifier: Programming Language :: Python :: 3.8
Classifier: Programming Language :: Python :: 3.9
Classifier: Programming Language :: Python :: 3.10
Requires-Python: >=3.7
License-File: LICENSE
Requires-Dist: dbt-core (>=1.6.0)
Requires-Dist: requests
